buf/__init__.py
buf/validate/__init__.py
buf/validate/validate_pb2.py
buf/validate/validate_pb2.pyi
buf/validate/validate_pb2_grpc.py
buf/validate/validate_pb2_grpc.pyi
google/__init__.py
google/api/__init__.py
google/api/annotations_pb2.py
google/api/annotations_pb2.pyi
google/api/annotations_pb2_grpc.py
google/api/annotations_pb2_grpc.pyi
google/api/field_behavior_pb2.py
google/api/field_behavior_pb2.pyi
google/api/field_behavior_pb2_grpc.py
google/api/field_behavior_pb2_grpc.pyi
google/api/http_pb2.py
google/api/http_pb2.pyi
google/api/http_pb2_grpc.py
google/api/http_pb2_grpc.pyi
protoc_gen_openapiv2/__init__.py
protoc_gen_openapiv2/options/__init__.py
protoc_gen_openapiv2/options/annotations_pb2.py
protoc_gen_openapiv2/options/annotations_pb2.pyi
protoc_gen_openapiv2/options/annotations_pb2_grpc.py
protoc_gen_openapiv2/options/annotations_pb2_grpc.pyi
protoc_gen_openapiv2/options/openapiv2_pb2.py
protoc_gen_openapiv2/options/openapiv2_pb2.pyi
protoc_gen_openapiv2/options/openapiv2_pb2_grpc.py
protoc_gen_openapiv2/options/openapiv2_pb2_grpc.pyi
sift/__init__.py
sift/annotation_logs/__init__.py
sift/annotation_logs/v1/__init__.py
sift/annotation_logs/v1/annotation_logs_pb2.py
sift/annotation_logs/v1/annotation_logs_pb2.pyi
sift/annotation_logs/v1/annotation_logs_pb2_grpc.py
sift/annotation_logs/v1/annotation_logs_pb2_grpc.pyi
sift/annotations/__init__.py
sift/annotations/v1/__init__.py
sift/annotations/v1/annotations_pb2.py
sift/annotations/v1/annotations_pb2.pyi
sift/annotations/v1/annotations_pb2_grpc.py
sift/annotations/v1/annotations_pb2_grpc.pyi
sift/api_keys/__init__.py
sift/api_keys/v2/__init__.py
sift/api_keys/v2/api_keys_pb2.py
sift/api_keys/v2/api_keys_pb2.pyi
sift/api_keys/v2/api_keys_pb2_grpc.py
sift/api_keys/v2/api_keys_pb2_grpc.pyi
sift/assets/__init__.py
sift/assets/v1/__init__.py
sift/assets/v1/assets_pb2.py
sift/assets/v1/assets_pb2.pyi
sift/assets/v1/assets_pb2_grpc.py
sift/assets/v1/assets_pb2_grpc.pyi
sift/calculated_channels/__init__.py
sift_stack_py-0.10.0.dist-info/LICENSE
sift_stack_py-0.10.0.dist-info/METADATA
sift_stack_py-0.10.0.dist-info/WHEEL
sift_stack_py-0.10.0.dist-info/top_level.txt
sift_stack_py-0.10.0.dist-info/RECORD
