Metadata-Version: 2.1
Name: sift_stack_py
Version: 0.10.0
Summary: Python client library for the Sift API
Maintainer-email: Sift Software Engineers <engineering@siftstack.com>
License: Copyright (c) 2024 Azimuth Industries Inc.
Project-URL: Homepage, https://github.com/sift-stack/sift/tree/main/python
Project-URL: Documentation, https://docs.siftstack.com/sift_py/sift_py.html
Project-URL: Repository, https://github.com/sift-stack/sift/tree/main/python
Project-URL: Changelog, https://github.com/sift-stack/sift/tree/main/python/CHANGELOG.md
Keywords: sift,sift-stack,siftstack,sift_py
Classifier: License :: OSI Approved :: MIT License
Classifier: Programming Language :: Python :: 3.8
Classifier: Programming Language :: Python :: 3.9
Classifier: Programming Language :: Python :: 3.10
Classifier: Programming Language :: Python :: 3.11
Classifier: Programming Language :: Python :: 3.12
Classifier: Programming Language :: Python :: 3.13
Classifier: Programming Language :: Python :: 3.14
Requires-Python: >=3.8
License-File: LICENSE
Requires-Dist: grpcio ~=1.13
Requires-Dist: PyYAML ~=6.0
Requires-Dist: pandas ~=2.0
Requires-Dist: protobuf >=5.0
Requires-Dist: pydantic ~=2.10
Requires-Dist: eval-type-backport ~=0.2
Requires-Dist: pydantic-core ~=2.3
Requires-Dist: requests ~=2.25
Requires-Dist: requests-toolbelt ~=1.0
Requires-Dist: alive-progress ~=3.0
Requires-Dist: pandas-stubs ~=2.0
Requires-Dist: types-PyYAML ~=6.0
Requires-Dist: types-protobuf >=5.0
Requires-Dist: typing-extensions ~=4.6
Requires-Dist: types-requests ~=2.25
Provides-Extra: all
Requires-Dist: cffi ~=1.14 ; extra == 'all'
Requires-Dist: h5py ~=3.11 ; extra == 'all'
Requires-Dist: npTDMS ~=1.9 ; extra == 'all'
Requires-Dist: polars ~=1.8 ; extra == 'all'
Requires-Dist: pyOpenSSL <24.0.0 ; extra == 'all'
Requires-Dist: pyarrow >=17.0.0 ; extra == 'all'
Requires-Dist: rosbags ~=0.0 ; extra == 'all'
Requires-Dist: sift-stream-bindings >=0.2.0-rc8 ; extra == 'all'
Requires-Dist: types-pyOpenSSL <24.0.0 ; extra == 'all'
Provides-Extra: build
Requires-Dist: build ==1.2.1 ; extra == 'build'
Requires-Dist: pdoc ==14.5.0 ; extra == 'build'
Provides-Extra: data-review
Requires-Dist: pyarrow >=17.0.0 ; extra == 'data-review'
Provides-Extra: dev
Requires-Dist: grpcio-testing ~=1.13 ; extra == 'dev'
Requires-Dist: mypy ==1.10.0 ; extra == 'dev'
Requires-Dist: pyright ==1.1.386 ; extra == 'dev'
Requires-Dist: pytest-asyncio ==0.23.7 ; extra == 'dev'
Requires-Dist: pytest-benchmark ==4.0.0 ; extra == 'dev'
Requires-Dist: pytest-dotenv ==0.5.2 ; extra == 'dev'
Requires-Dist: pytest-mock ==3.14.0 ; extra == 'dev'
Requires-Dist: pytest ==8.2.2 ; extra == 'dev'
Requires-Dist: ruff ~=0.12.10 ; extra == 'dev'
Requires-Dist: tomlkit ~=0.13.3 ; extra == 'dev'
Provides-Extra: dev-all
Requires-Dist: build ==1.2.1 ; extra == 'dev-all'
Requires-Dist: cffi ~=1.14 ; extra == 'dev-all'
Requires-Dist: grpcio-testing ~=1.13 ; extra == 'dev-all'
Requires-Dist: h5py ~=3.11 ; extra == 'dev-all'
Requires-Dist: mypy ==1.10.0 ; extra == 'dev-all'
Requires-Dist: npTDMS ~=1.9 ; extra == 'dev-all'
Requires-Dist: pdoc ==14.5.0 ; extra == 'dev-all'
Requires-Dist: polars ~=1.8 ; extra == 'dev-all'
Requires-Dist: pyOpenSSL <24.0.0 ; extra == 'dev-all'
Requires-Dist: pyarrow >=17.0.0 ; extra == 'dev-all'
Requires-Dist: pyright ==1.1.386 ; extra == 'dev-all'
Requires-Dist: pytest-asyncio ==0.23.7 ; extra == 'dev-all'
Requires-Dist: pytest-benchmark ==4.0.0 ; extra == 'dev-all'
Requires-Dist: pytest-dotenv ==0.5.2 ; extra == 'dev-all'
Requires-Dist: pytest-mock ==3.14.0 ; extra == 'dev-all'
Requires-Dist: pytest ==8.2.2 ; extra == 'dev-all'
Requires-Dist: rosbags ~=0.0 ; extra == 'dev-all'
Requires-Dist: ruff ~=0.12.10 ; extra == 'dev-all'
Requires-Dist: sift-stream-bindings >=0.2.0-rc8 ; extra == 'dev-all'
Requires-Dist: tomlkit ~=0.13.3 ; extra == 'dev-all'
Requires-Dist: types-pyOpenSSL <24.0.0 ; extra == 'dev-all'
Provides-Extra: development
Requires-Dist: grpcio-testing ~=1.13 ; extra == 'development'
Requires-Dist: mypy ==1.10.0 ; extra == 'development'
Requires-Dist: pyright ==1.1.386 ; extra == 'development'
Requires-Dist: pytest-asyncio ==0.23.7 ; extra == 'development'
Requires-Dist: pytest-benchmark ==4.0.0 ; extra == 'development'
Requires-Dist: pytest-dotenv ==0.5.2 ; extra == 'development'
Requires-Dist: pytest-mock ==3.14.0 ; extra == 'development'
Requires-Dist: pytest ==8.2.2 ; extra == 'development'
Requires-Dist: ruff ~=0.12.10 ; extra == 'development'
Requires-Dist: tomlkit ~=0.13.3 ; extra == 'development'
Provides-Extra: docs
Requires-Dist: griffe-pydantic ; extra == 'docs'
Requires-Dist: mike ; extra == 'docs'
Requires-Dist: mkdocs ; extra == 'docs'
Requires-Dist: mkdocs-api-autonav ; extra == 'docs'
Requires-Dist: mkdocs-include-markdown-plugin ; extra == 'docs'
Requires-Dist: mkdocs-jupyter ; extra == 'docs'
Requires-Dist: mkdocs-material ; extra == 'docs'
Requires-Dist: mkdocstrings[python] ; extra == 'docs'
Provides-Extra: docs-build
Requires-Dist: build ==1.2.1 ; extra == 'docs-build'
Requires-Dist: cffi ~=1.14 ; extra == 'docs-build'
Requires-Dist: griffe-pydantic ; extra == 'docs-build'
Requires-Dist: grpcio-testing ~=1.13 ; extra == 'docs-build'
Requires-Dist: h5py ~=3.11 ; extra == 'docs-build'
Requires-Dist: mike ; extra == 'docs-build'
Requires-Dist: mkdocs ; extra == 'docs-build'
Requires-Dist: mkdocs-api-autonav ; extra == 'docs-build'
Requires-Dist: mkdocs-include-markdown-plugin ; extra == 'docs-build'
Requires-Dist: mkdocs-jupyter ; extra == 'docs-build'
Requires-Dist: mkdocs-material ; extra == 'docs-build'
Requires-Dist: mkdocstrings[python] ; extra == 'docs-build'
Requires-Dist: mypy ==1.10.0 ; extra == 'docs-build'
Requires-Dist: npTDMS ~=1.9 ; extra == 'docs-build'
Requires-Dist: pdoc ==14.5.0 ; extra == 'docs-build'
Requires-Dist: polars ~=1.8 ; extra == 'docs-build'
Requires-Dist: pyOpenSSL <24.0.0 ; extra == 'docs-build'
Requires-Dist: pyarrow >=17.0.0 ; extra == 'docs-build'
Requires-Dist: pyright ==1.1.386 ; extra == 'docs-build'
Requires-Dist: pytest-asyncio ==0.23.7 ; extra == 'docs-build'
Requires-Dist: pytest-benchmark ==4.0.0 ; extra == 'docs-build'
Requires-Dist: pytest-dotenv ==0.5.2 ; extra == 'docs-build'
Requires-Dist: pytest-mock ==3.14.0 ; extra == 'docs-build'
Requires-Dist: pytest ==8.2.2 ; extra == 'docs-build'
Requires-Dist: rosbags ~=0.0 ; extra == 'docs-build'
Requires-Dist: ruff ~=0.12.10 ; extra == 'docs-build'
Requires-Dist: sift-stream-bindings >=0.2.0-rc8 ; extra == 'docs-build'
Requires-Dist: tomlkit ~=0.13.3 ; extra == 'docs-build'
Requires-Dist: types-pyOpenSSL <24.0.0 ; extra == 'docs-build'
Provides-Extra: file-imports
Requires-Dist: h5py ~=3.11 ; extra == 'file-imports'
Requires-Dist: npTDMS ~=1.9 ; extra == 'file-imports'
Requires-Dist: polars ~=1.8 ; extra == 'file-imports'
Requires-Dist: rosbags ~=0.0 ; extra == 'file-imports'
Provides-Extra: hdf5
Requires-Dist: h5py ~=3.11 ; extra == 'hdf5'
Requires-Dist: polars ~=1.8 ; extra == 'hdf5'
Provides-Extra: openssl
Requires-Dist: cffi ~=1.14 ; extra == 'openssl'
Requires-Dist: pyOpenSSL <24.0.0 ; extra == 'openssl'
Requires-Dist: types-pyOpenSSL <24.0.0 ; extra == 'openssl'
Provides-Extra: rosbags
Requires-Dist: rosbags ~=0.0 ; extra == 'rosbags'
Provides-Extra: sift-stream
Requires-Dist: sift-stream-bindings >=0.2.0-rc8 ; extra == 'sift-stream'
Provides-Extra: sift-stream-bindings
Requires-Dist: sift-stream-bindings >=0.2.0-rc8 ; extra == 'sift-stream-bindings'
Provides-Extra: tdms
Requires-Dist: npTDMS ~=1.9 ; extra == 'tdms'
